bitcategory/__init__.py
bitcategory/fields.py
bitcategory/models.py
bitcategory/tests.py
bitcategory/urls.py
bitcategory/views.py
bitcategory/widgets.py
bitcategory/static/bitcategory/hierarchicalwidget.js
django_bit_category-0.5.2.dist-info/DESCRIPTION.rst
django_bit_category-0.5.2.dist-info/METADATA
django_bit_category-0.5.2.dist-info/RECORD
django_bit_category-0.5.2.dist-info/WHEEL
django_bit_category-0.5.2.dist-info/metadata.json
django_bit_category-0.5.2.dist-info/top_level.txt
