Metadata-Version: 2.0
Name: django-bit-category
Version: 0.5.2
Summary: Django category app with bitwise tree-like structure of primary key.
Home-page: http://pypi.python.org/pypi/django-bit-category/
Author: Tomas Peterka
Author-email: prestizni@gmail.com
License: GPL v3
Keywords: django category hierarchy
Platform: UNKNOWN
Requires-Dist: django (>=1.5)
